spaceone/__init__.py
spaceone/api/__init__.py
spaceone/api/board/__init__.py
spaceone/api/board/v1/__init__.py
spaceone/api/board/v1/board_pb2.py
spaceone/api/board/v1/board_pb2_grpc.py
spaceone/api/board/v1/post_pb2.py
spaceone/api/board/v1/post_pb2_grpc.py
spaceone/api/config/__init__.py
spaceone/api/config/v1/__init__.py
spaceone/api/config/v1/domain_config_pb2.py
spaceone/api/config/v1/domain_config_pb2_grpc.py
spaceone/api/config/v1/user_config_pb2.py
spaceone/api/config/v1/user_config_pb2_grpc.py
spaceone/api/core/__init__.py
spaceone/api/core/v1/__init__.py
spaceone/api/core/v1/handler_pb2.py
spaceone/api/core/v1/handler_pb2_grpc.py
spaceone/api/core/v1/query_pb2.py
spaceone/api/core/v1/query_pb2_grpc.py
spaceone/api/core/v1/server_info_pb2.py
spaceone/api/core/v1/server_info_pb2_grpc.py
spaceone/api/cost_analysis/__init__.py
spaceone/api/cost_analysis/plugin/__init__.py
spaceone/api/cost_analysis/plugin/cost_pb2.py
spaceone/api/cost_analysis/plugin/cost_pb2_grpc.py
spaceone/api/cost_analysis/plugin/data_source_pb2.py
spaceone/api/cost_analysis/plugin/data_source_pb2_grpc.py
spaceone/api/cost_analysis/plugin/job_pb2.py
spaceone/api/cost_analysis/plugin/job_pb2_grpc.py
spaceone/api/cost_analysis/v1/__init__.py
spaceone/api/cost_analysis/v1/budget_pb2.py
spaceone/api/cost_analysis/v1/budget_pb2_grpc.py
spaceone/api/cost_analysis/v1/budget_usage_pb2.py
spaceone/api/cost_analysis/v1/budget_usage_pb2_grpc.py
spaceone/api/cost_analysis/v1/cost_pb2.py
spaceone/api/cost_analysis/v1/cost_pb2_grpc.py
spaceone/api/cost_analysis/v1/cost_query_set_pb2.py
spaceone/api/cost_analysis/v1/cost_query_set_pb2_grpc.py
spaceone/api/cost_analysis/v1/custom_widget_pb2.py
spaceone/api/cost_analysis/v1/custom_widget_pb2_grpc.py
spaceone/api/cost_analysis/v1/data_source_pb2.py
spaceone/api/cost_analysis/v1/data_source_pb2_grpc.py
spaceone/api/cost_analysis/v1/data_source_rule_pb2.py
spaceone/api/cost_analysis/v1/data_source_rule_pb2_grpc.py
spaceone/api/cost_analysis/v1/job_pb2.py
immin5-1.0.0.dist-info/METADATA
immin5-1.0.0.dist-info/WHEEL
immin5-1.0.0.dist-info/top_level.txt
immin5-1.0.0.dist-info/RECORD
