Metadata-Version: 2.1
Name: immin5
Version: 1.0.0
Summary: Coreforet API Protobuf
Home-page: https://cloudforet.io/
Author: MEGAZONE Cloud Corp.
Author-email: admin@spaceone.dev
License: Apache Software License
Platform: UNKNOWN
